README.md
setup.py
ezmysql/SqlTemplate.py
ezmysql/TableCache.py
ezmysql/__init__.py
ezmysql/operation/SqlOperation.py
ezmysql/operation/TableOperation.py
ezmysql/operation/__init__.py
ezmysql/sqlbuilder/SqlBuilder.py
ezmysql/sqlbuilder/__init__.py
ezmysql/utils/PageUtils.py
ezmysql/utils/__init__.py
yixsoft_ezmysql.egg-info/PKG-INFO
yixsoft_ezmysql.egg-info/SOURCES.txt
yixsoft_ezmysql.egg-info/dependency_links.txt
yixsoft_ezmysql.egg-info/requires.txt
yixsoft_ezmysql.egg-info/top_level.txt